silverriver/__init__.py
silverriver/client/__init__.py
silverriver/client/agent_endpoints.py
silverriver/client/browser_endpoints.py
silverriver/client/endpoint.py
silverriver/client/http_client.py
silverriver/interfaces/__init__.py
silverriver/interfaces/base_agent.py
silverriver/interfaces/chat.py
silverriver/interfaces/data_models.py
silverriver/modules/__init__.py
silverriver/modules/users/__init__.py
silverriver/utils/__init__.py
silverriver/utils/execution.py
silverriver/utils/remote_browser.py
silverflow-0.1.3.dist-info/METADATA
silverflow-0.1.3.dist-info/WHEEL
silverflow-0.1.3.dist-info/top_level.txt
silverflow-0.1.3.dist-info/RECORD
