Metadata-Version: 2.1
Name: silverflow
Version: 0.1.3
Summary: SilverRiver SDK for advanced automation and AI-driven tasks
Author: Silvestro
Author-email: hello@silverstream.ai
Classifier: Development Status :: 3 - Alpha
Classifier: Intended Audience :: Developers
Classifier: License :: OSI Approved :: MIT License
Classifier: Operating System :: OS Independent
Requires-Python: >=3.10
Requires-Dist: httpx==0.27.2
Requires-Dist: playwright==1.46.0
Requires-Dist: pydantic==2.8.2
Requires-Dist: python-dotenv==1.0.1
Requires-Dist: slack-sdk==3.31.0
Requires-Dist: tabulate==0.9.0
